{"stats":{"minecraft:picked_up":{"minecraft:coarse_dirt":3,"minecraft:kelp":1,"god:scrollof_life":3,"minecraft:brown_mushroom":1,"death_angels:death_angel_meat":1,"minecraft:sand":6,"minecraft:spruce_log":5,"minecraft:dirt":32},"minecraft:mined":{"minecraft:large_fern":2,"minecraft:podzol":26,"minecraft:grass":1,"minecraft:coarse_dirt":3,"minecraft:brown_mushroom":1,"minecraft:sand":6,"minecraft:dirt":6,"minecraft:fire":7,"minecraft:spruce_log":5,"minecraft:fern":1},"minecraft:killed_by":{"man:managgresive":1,"antlers:wendigo":1},"minecraft:custom":{"minecraft:time_since_rest":1843,"minecraft:play_time":12126,"minecraft:sprint_one_cm":25934,"minecraft:damage_taken":1538,"minecraft:walk_one_cm":30397,"minecraft:deaths":4,"minecraft:sneak_time":20,"minecraft:walk_under_water_one_cm":3542,"minecraft:jump":182,"minecraft:leave_game":4,"minecraft:time_since_death":1710,"minecraft:walk_on_water_one_cm":5832,"minecraft:total_world_time":12126,"minecraft:damage_resisted":282,"minecraft:swim_one_cm":10239,"minecraft:fly_one_cm":29227,"minecraft:fall_one_cm":10931},"minecraft:used":{"minecraft:dirt":1,"minecraft:sand":5,"death_angels:death_angel_meat":1}},"DataVersion":3465}